tree_sitter_nuon/__init__.py
tree_sitter_nuon/__init__.pyi
tree_sitter_nuon/_binding.abi3.so
tree_sitter_nuon/binding.c
tree_sitter_nuon/py.typed
tree_sitter_nuon/queries/highlights.scm
tree_sitter_nuon-0.22.1.dist-info/METADATA
tree_sitter_nuon-0.22.1.dist-info/WHEEL
tree_sitter_nuon-0.22.1.dist-info/top_level.txt
tree_sitter_nuon-0.22.1.dist-info/RECORD
tree_sitter_nuon-0.22.1.dist-info/licenses/LICENSE
