Metadata-Version: 2.4
Name: tree-sitter-nuon
Version: 0.22.1
Summary:  NUON grammar for tree-sitter 
Author-email:  Mel Massadian  <mel@melmassadian.com>
License: MIT
Project-URL: Homepage, https://github.com/melmass/tree-sitter-nuon
Keywords: incremental,parsing,tree-sitter,nuon
Classifier: Intended Audience :: Developers
Classifier: Topic :: Software Development :: Compilers
Classifier: Topic :: Text Processing :: Linguistic
Classifier: Typing :: Typed
Requires-Python: >=3.10
License-File: LICENSE
Provides-Extra: core
Requires-Dist: tree-sitter~=0.24; extra == "core"
Dynamic: license-file
